{"expireTime":9007200883706341000,"key":"gatsby-plugin-mdx-entire-payload-717197b8fd7d2f1b4a310af67a83fb74--undefined","val":{"mdast":{"type":"root","children":[{"type":"heading","depth":2,"children":[{"type":"text","value":"C Implementation","position":{"start":{"line":2,"column":4,"offset":5},"end":{"line":2,"column":20,"offset":21},"indent":[]}}],"position":{"start":{"line":2,"column":1,"offset":2},"end":{"line":2,"column":20,"offset":21},"indent":[]}},{"type":"heading","depth":3,"children":[{"type":"text","value":"30. Write a C program to check whether two matrices are equal or not.","position":{"start":{"line":3,"column":5,"offset":27},"end":{"line":3,"column":74,"offset":96},"indent":[]}}],"position":{"start":{"line":3,"column":1,"offset":23},"end":{"line":3,"column":74,"offset":96},"indent":[]}},{"type":"code","lang":"c","meta":null,"value":"//Write a C program to check whether two matrices are equal or not.\n#include <stdio.h>\nint main()\n{\n   int arr1[50][50], brr1[50][50],i, j, r1, c1, r2, c2, a =1;\n   printf(\"Input Rows and Columns of the 1st matrix :\\n\");\n   scanf(\"%d %d\", &r1, &c1);\n\n   printf(\"Input Rows and Columns of the 2nd matrix :\\n\");\n   scanf(\"%d %d\", &r2,&c2);\n     printf(\"Input elements in the first matrix :\\n\");\n       for(i=0;i<r1;i++)\n        {\n            for(j=0;j<c1;j++)\n            {\n               printf(\"element - [%d],[%d] : \",i,j);\n               scanf(\"%d\",&arr1[i][j]);\n            }\n        }\n       printf(\"Input elements in the second matrix :\\n\");\n       for(i=0;i<r2;i++)\n        {\n            for(j=0;j<c2;j++)\n            {\n               printf(\"element - [%d],[%d] : \",i,j);\n               scanf(\"%d\",&brr1[i][j]);\n            }\n        }\n      printf(\"The first matrix is :\\n\");\n     for(i=0;i<r1;i++)\n     {\n       for(j=0;j<c1 ;j++)\n         printf(\" %d \",arr1[i][j]);\n        printf(\"\\n\");\n     }\n     printf(\"The second matrix is :\\n\");\n     for(i=0;i<r2;i++)\n     {\n       for(j=0;j<c2 ;j++)\n         printf(\" %d \",brr1[i][j]);\n        printf(\"\\n\");\n     }\n   if(r1 == r2 && c1 == c2)\n   {\n        printf(\"The Matrices can be compared. \\n\");\n        for(i=0; i<r1; i++)\n        {\n             for(j=0; j<c2; j++)\n             {\n            if(arr1[i][j] != brr1[i][j])\n            {\n                   a = 0;\n                   break;\n            }\n             }\n          }\n    }\n    else\n    {  printf(\"The Matrices Cannot be compared :\\n\");\n       exit(1);\n    }\n    if(a == 1 )\n    printf(\"Two matrices are equal.\");\n    else\n    printf(\"But,two matrices are not equal.\");\n}","position":{"start":{"line":4,"column":1,"offset":98},"end":{"line":71,"column":4,"offset":1863},"indent":[1,1,1,1,1,1,1,1,1,1,1,1,1,1,1,1,1,1,1,1,1,1,1,1,1,1,1,1,1,1,1,1,1,1,1,1,1,1,1,1,1,1,1,1,1,1,1,1,1,1,1,1,1,1,1,1,1,1,1,1,1,1,1,1,1,1,1]}},{"type":"heading","depth":3,"children":[{"type":"text","value":"Output","position":{"start":{"line":72,"column":5,"offset":1869},"end":{"line":72,"column":11,"offset":1875},"indent":[]}}],"position":{"start":{"line":72,"column":1,"offset":1865},"end":{"line":72,"column":11,"offset":1875},"indent":[]}},{"type":"code","lang":null,"meta":null,"value":"Input Rows and Columns of the 1st matrix :\n2 2\nInput Rows and Columns of the 2nd matrix :\n2 2\nInput elements in the first matrix :\nelement - [0],[0] : 1\nelement - [0],[1] : 2\nelement - [1],[0] : 3\nelement - [1],[1] : 4\nInput elements in the second matrix :\nelement - [0],[0] : 5\nelement - [0],[1] : 6\nelement - [1],[0] : 7\nelement - [1],[1] : 8\nThe first matrix is :\n 1  2\n 3  4\nThe second matrix is :\n 5  6\n 7  8\nThe Matrices can be compared.\nBut,two matrices are not equal.","position":{"start":{"line":73,"column":1,"offset":1877},"end":{"line":96,"column":4,"offset":2383},"indent":[1,1,1,1,1,1,1,1,1,1,1,1,1,1,1,1,1,1,1,1,1,1,1]}},{"type":"heading","depth":2,"children":[{"type":"text","value":"C++ Implementation","position":{"start":{"line":97,"column":4,"offset":2388},"end":{"line":97,"column":22,"offset":2406},"indent":[]}}],"position":{"start":{"line":97,"column":1,"offset":2385},"end":{"line":97,"column":22,"offset":2406},"indent":[]}},{"type":"heading","depth":3,"children":[{"type":"text","value":"30. Write a C++ program to check whether two matrices are equal or not.","position":{"start":{"line":98,"column":5,"offset":2412},"end":{"line":98,"column":76,"offset":2483},"indent":[]}}],"position":{"start":{"line":98,"column":1,"offset":2408},"end":{"line":98,"column":76,"offset":2483},"indent":[]}},{"type":"code","lang":"c","meta":null,"value":"//Write a C++ program to check whether two matrices are equal or not.\n\n#include <iostream>\nusing namespace std;\nint  main()\n{\n   int arr1[50][50], brr1[50][50],i, j, r1, c1, r2, c2, a =1;\n   cout << \"Input Rows and Columns of the 1st matrix :\\n\";\n   scanf(\"%d %d\", &r1, &c1);\n   cout << \"Input Rows and Columns of the 2nd matrix :\\n\";\n   cin >> r2 >> c2;\n     cout << \"Input elements in the first matrix :\\n\";\n       for(i=0;i<r1;i++)\n        {\n            for(j=0;j<c1;j++)\n            {\n               cout << \"element -  : [\" << i << \"][\" << j <<\"]\";\n               cin >> arr1[i][j];\n            }\n        }\n       cout << \"Input elements in the second matrix :\\n\";\n       for(i=0;i<r2;i++)\n        {\n            for(j=0;j<c2;j++)\n            {\n               cout << \"element -  : [\" << i << \"][\" << j <<\"]\";\n               cin >> brr1[i][j];\n            }\n        }\n     cout << \"The first matrix is :\\n\";\n     for(i=0;i<r1;i++)\n     {\n       for(j=0;j<c1 ;j++)\n         cout << \" \" << arr1[i][j] << \" \";\n       cout << \"\\n\";\n     }\n     cout << \"The second matrix is :\\n\";\n     for(i=0;i<r2;i++)\n     {\n       for(j=0;j<c2 ;j++)\n         cout << \" \" << brr1[i][j] << \" \";\n        cout << \"\\n\";\n     }\n    if(r1 == r2 && c1 == c2)\n    {\n        cout << \"The Matrices can be compared. \\n\";\n        for(i=0; i<r1; i++)\n        {\n            for(j=0; j<c2; j++)\n            {\n            if(arr1[i][j] != brr1[i][j])\n            {\n                   a = 0;\n                   break;\n            }\n            }\n          }\n    }\n    else\n    {  cout << \"The Matrices Cannot be compared :\\n\";\n       exit(1);\n    }\n    if(a == 1 )\n    cout << \"Two matrices are equal.\";\n    else\n    cout << \"But,two matrices are not equal.\";\n}","position":{"start":{"line":99,"column":1,"offset":2485},"end":{"line":167,"column":4,"offset":4291},"indent":[1,1,1,1,1,1,1,1,1,1,1,1,1,1,1,1,1,1,1,1,1,1,1,1,1,1,1,1,1,1,1,1,1,1,1,1,1,1,1,1,1,1,1,1,1,1,1,1,1,1,1,1,1,1,1,1,1,1,1,1,1,1,1,1,1,1,1,1]}},{"type":"heading","depth":3,"children":[{"type":"text","value":"Output","position":{"start":{"line":168,"column":5,"offset":4297},"end":{"line":168,"column":11,"offset":4303},"indent":[]}}],"position":{"start":{"line":168,"column":1,"offset":4293},"end":{"line":168,"column":11,"offset":4303},"indent":[]}},{"type":"code","lang":null,"meta":null,"value":"Input Rows and Columns of the 1st matrix :\n2 2\nInput Rows and Columns of the 2nd matrix :\n2 2\nInput elements in the first matrix :\nelement - [0],[0] : 1\nelement - [0],[1] : 2\nelement - [1],[0] : 3\nelement - [1],[1] : 4\nInput elements in the second matrix :\nelement - [0],[0] : 5\nelement - [0],[1] : 6\nelement - [1],[0] : 7\nelement - [1],[1] : 8\nThe first matrix is :\n 1  2\n 3  4\nThe second matrix is :\n 5  6\n 7  8\nThe Matrices can be compared.\nBut,two matrices are not equal.","position":{"start":{"line":169,"column":1,"offset":4305},"end":{"line":192,"column":4,"offset":4811},"indent":[1,1,1,1,1,1,1,1,1,1,1,1,1,1,1,1,1,1,1,1,1,1,1]}},{"type":"heading","depth":2,"children":[{"type":"text","value":"Java Implementation","position":{"start":{"line":194,"column":4,"offset":4818},"end":{"line":194,"column":23,"offset":4837},"indent":[]}}],"position":{"start":{"line":194,"column":1,"offset":4815},"end":{"line":194,"column":23,"offset":4837},"indent":[]}},{"type":"heading","depth":3,"children":[{"type":"text","value":"30. Write a Java program to check whether two matrices are equal or not.","position":{"start":{"line":195,"column":5,"offset":4843},"end":{"line":195,"column":77,"offset":4915},"indent":[]}}],"position":{"start":{"line":195,"column":1,"offset":4839},"end":{"line":195,"column":77,"offset":4915},"indent":[]}},{"type":"code","lang":"js","meta":null,"value":"//Write a Java program to check whether two matrices are equal or not.\nimport java.util.Scanner;\npublic class Funycode {\n    public static void main(String[] args) {\n           Scanner z=new Scanner(System.in);\n           int arr1[][]= new int[3][3],brr1[][] = new int[3][3],i, j, r1, c1, r2, c2, a =1;\n           System.out.println(\"Input Rows and Columns of the 1st matrix :\\n\");\n           r1 = z.nextInt();\n           c1 = z.nextInt();\n           System.out.println(\"Input Rows and Columns of the 2nd matrix :\\n\");\n           r2 = z.nextInt();\n           c2 = z.nextInt();\n             System.out.println(\"Input elements in the first matrix :\\n\");\n               for(i=0;i<r1;i++)\n                {\n                    for(j=0;j<c1;j++)\n                    {\n                       System.out.println(\"element - : \"+\"[\"+i+\"]\"+\"[\"+j+\"]\");\n                       arr1[i][j] = z.nextInt();\n                    }\n                }\n               System.out.println(\"Input elements in the second matrix :\\n\");\n               for(i=0;i<r2;i++)\n                {\n                    for(j=0;j<c2;j++)\n                    {\n                       System.out.println(\"element - : \"+\"[\"+i+\"]\"+\"[\"+j+\"]\");\n                       brr1[i][j] = z.nextInt();\n                    }\n                }\n              System.out.println(\"The first matrix is :\\n\");\n             for(i=0;i<r1;i++)\n             {\n               for(j=0;j<c1 ;j++)\n                 System.out.printf(\" \"+arr1[i][j]+\" \");\n                System.out.printf(\"\\n\");\n             }\n             System.out.println(\"The second matrix is :\\n\");\n             for(i=0;i<r2;i++)\n             {\n               for(j=0;j<c2 ;j++)\n                 System.out.printf(\" \"+brr1[i][j]+\" \");\n                System.out.printf(\"\\n\");\n             }\n           if(r1 == r2 && c1 == c2)\n           {\n                System.out.println(\"The Matrices can be compared. \\n\");\n                for(i=0; i<r1; i++)\n                {\n                     for(j=0; j<c2; j++)\n                     {\n                        if(arr1[i][j] != brr1[i][j])\n                        {\n                               a = 0;\n                               break;\n                        }\n                     }\n                  }\n            }\n            else\n            {\n               System.out.println(\"The Matrices Cannot be compared :\\n\");\n               System.exit(1);\n            }\n            if(a == 1 )\n              System.out.println(\"Two matrices are equal.\");\n            else\n              System.out.println(\"But,two matrices are not equal.\");\n      }\n}","position":{"start":{"line":196,"column":1,"offset":4917},"end":{"line":267,"column":4,"offset":7599},"indent":[1,1,1,1,1,1,1,1,1,1,1,1,1,1,1,1,1,1,1,1,1,1,1,1,1,1,1,1,1,1,1,1,1,1,1,1,1,1,1,1,1,1,1,1,1,1,1,1,1,1,1,1,1,1,1,1,1,1,1,1,1,1,1,1,1,1,1,1,1,1,1]}},{"type":"heading","depth":3,"children":[{"type":"text","value":"Output","position":{"start":{"line":268,"column":5,"offset":7605},"end":{"line":268,"column":11,"offset":7611},"indent":[]}}],"position":{"start":{"line":268,"column":1,"offset":7601},"end":{"line":268,"column":11,"offset":7611},"indent":[]}},{"type":"code","lang":null,"meta":null,"value":"Input Rows and Columns of the 1st matrix :\n2 2\nInput Rows and Columns of the 2nd matrix :\n2 2\nInput elements in the first matrix :\nelement - [0],[0] : 1\nelement - [0],[1] : 2\nelement - [1],[0] : 3\nelement - [1],[1] : 4\nInput elements in the second matrix :\nelement - [0],[0] : 5\nelement - [0],[1] : 6\nelement - [1],[0] : 7\nelement - [1],[1] : 8\nThe first matrix is :\n 1  2\n 3  4\nThe second matrix is :\n 5  6\n 7  8\nThe Matrices can be compared.\nBut,two matrices are not equal.","position":{"start":{"line":269,"column":1,"offset":7613},"end":{"line":292,"column":4,"offset":8119},"indent":[1,1,1,1,1,1,1,1,1,1,1,1,1,1,1,1,1,1,1,1,1,1,1]}},{"type":"export","value":"export const _frontmatter = {\"title\":\"Write a C/C++/Java program to check whether two matrices are equal or not.\",\"category\":\"Array Program Index\",\"tags\":[\"#c\",\"#c++\",\"#java\",\"#tutorial\"],\"date\":\"2020-04-16T00:00:00.000Z\",\"thumbnailText\":\"Index\"}","position":{"start":{"line":295,"column":1,"offset":8123},"end":{"line":295,"column":247,"offset":8369},"indent":[]}}],"position":{"start":{"line":1,"column":1,"offset":0},"end":{"line":295,"column":247,"offset":8369}}},"scopeImports":["import * as React from 'react'"],"scopeIdentifiers":["React"],"body":"var _excluded = [\"components\"];\n\nfunction _extends() { _extends = Object.assign || function (target) { for (var i = 1; i < arguments.length; i++) { var source = arguments[i]; for (var key in source) { if (Object.prototype.hasOwnProperty.call(source, key)) { target[key] = source[key]; } } } return target; }; return _extends.apply(this, arguments); }\n\nfunction _objectWithoutProperties(source, excluded) { if (source == null) return {}; var target = _objectWithoutPropertiesLoose(source, excluded); var key, i; if (Object.getOwnPropertySymbols) { var sourceSymbolKeys = Object.getOwnPropertySymbols(source); for (i = 0; i < sourceSymbolKeys.length; i++) { key = sourceSymbolKeys[i]; if (excluded.indexOf(key) >= 0) continue; if (!Object.prototype.propertyIsEnumerable.call(source, key)) continue; target[key] = source[key]; } } return target; }\n\nfunction _objectWithoutPropertiesLoose(source, excluded) { if (source == null) return {}; var target = {}; var sourceKeys = Object.keys(source); var key, i; for (i = 0; i < sourceKeys.length; i++) { key = sourceKeys[i]; if (excluded.indexOf(key) >= 0) continue; target[key] = source[key]; } return target; }\n\n/* @jsxRuntime classic */\n\n/* @jsx mdx */\nvar _frontmatter = {\n  \"title\": \"Write a C/C++/Java program to check whether two matrices are equal or not.\",\n  \"category\": \"Array Program Index\",\n  \"tags\": [\"#c\", \"#c++\", \"#java\", \"#tutorial\"],\n  \"date\": \"2020-04-16T00:00:00.000Z\",\n  \"thumbnailText\": \"Index\"\n};\nvar layoutProps = {\n  _frontmatter: _frontmatter\n};\nvar MDXLayout = \"wrapper\";\nreturn function MDXContent(_ref) {\n  var components = _ref.components,\n      props = _objectWithoutProperties(_ref, _excluded);\n\n  return mdx(MDXLayout, _extends({}, layoutProps, props, {\n    components: components,\n    mdxType: \"MDXLayout\"\n  }), mdx(\"h2\", null, \"C Implementation\"), mdx(\"h3\", null, \"30. Write a C program to check whether two matrices are equal or not.\"), mdx(\"pre\", null, mdx(\"code\", {\n    parentName: \"pre\",\n    \"className\": \"language-c\"\n  }, \"//Write a C program to check whether two matrices are equal or not.\\n#include <stdio.h>\\nint main()\\n{\\n   int arr1[50][50], brr1[50][50],i, j, r1, c1, r2, c2, a =1;\\n   printf(\\\"Input Rows and Columns of the 1st matrix :\\\\n\\\");\\n   scanf(\\\"%d %d\\\", &r1, &c1);\\n\\n   printf(\\\"Input Rows and Columns of the 2nd matrix :\\\\n\\\");\\n   scanf(\\\"%d %d\\\", &r2,&c2);\\n     printf(\\\"Input elements in the first matrix :\\\\n\\\");\\n       for(i=0;i<r1;i++)\\n        {\\n            for(j=0;j<c1;j++)\\n            {\\n               printf(\\\"element - [%d],[%d] : \\\",i,j);\\n               scanf(\\\"%d\\\",&arr1[i][j]);\\n            }\\n        }\\n       printf(\\\"Input elements in the second matrix :\\\\n\\\");\\n       for(i=0;i<r2;i++)\\n        {\\n            for(j=0;j<c2;j++)\\n            {\\n               printf(\\\"element - [%d],[%d] : \\\",i,j);\\n               scanf(\\\"%d\\\",&brr1[i][j]);\\n            }\\n        }\\n      printf(\\\"The first matrix is :\\\\n\\\");\\n     for(i=0;i<r1;i++)\\n     {\\n       for(j=0;j<c1 ;j++)\\n         printf(\\\" %d \\\",arr1[i][j]);\\n        printf(\\\"\\\\n\\\");\\n     }\\n     printf(\\\"The second matrix is :\\\\n\\\");\\n     for(i=0;i<r2;i++)\\n     {\\n       for(j=0;j<c2 ;j++)\\n         printf(\\\" %d \\\",brr1[i][j]);\\n        printf(\\\"\\\\n\\\");\\n     }\\n   if(r1 == r2 && c1 == c2)\\n   {\\n        printf(\\\"The Matrices can be compared. \\\\n\\\");\\n        for(i=0; i<r1; i++)\\n        {\\n             for(j=0; j<c2; j++)\\n             {\\n            if(arr1[i][j] != brr1[i][j])\\n            {\\n                   a = 0;\\n                   break;\\n            }\\n             }\\n          }\\n    }\\n    else\\n    {  printf(\\\"The Matrices Cannot be compared :\\\\n\\\");\\n       exit(1);\\n    }\\n    if(a == 1 )\\n    printf(\\\"Two matrices are equal.\\\");\\n    else\\n    printf(\\\"But,two matrices are not equal.\\\");\\n}\\n\")), mdx(\"h3\", null, \"Output\"), mdx(\"pre\", null, mdx(\"code\", {\n    parentName: \"pre\"\n  }, \"Input Rows and Columns of the 1st matrix :\\n2 2\\nInput Rows and Columns of the 2nd matrix :\\n2 2\\nInput elements in the first matrix :\\nelement - [0],[0] : 1\\nelement - [0],[1] : 2\\nelement - [1],[0] : 3\\nelement - [1],[1] : 4\\nInput elements in the second matrix :\\nelement - [0],[0] : 5\\nelement - [0],[1] : 6\\nelement - [1],[0] : 7\\nelement - [1],[1] : 8\\nThe first matrix is :\\n 1  2\\n 3  4\\nThe second matrix is :\\n 5  6\\n 7  8\\nThe Matrices can be compared.\\nBut,two matrices are not equal.\\n\")), mdx(\"h2\", null, \"C++ Implementation\"), mdx(\"h3\", null, \"30. Write a C++ program to check whether two matrices are equal or not.\"), mdx(\"pre\", null, mdx(\"code\", {\n    parentName: \"pre\",\n    \"className\": \"language-c\"\n  }, \"//Write a C++ program to check whether two matrices are equal or not.\\n\\n#include <iostream>\\nusing namespace std;\\nint  main()\\n{\\n   int arr1[50][50], brr1[50][50],i, j, r1, c1, r2, c2, a =1;\\n   cout << \\\"Input Rows and Columns of the 1st matrix :\\\\n\\\";\\n   scanf(\\\"%d %d\\\", &r1, &c1);\\n   cout << \\\"Input Rows and Columns of the 2nd matrix :\\\\n\\\";\\n   cin >> r2 >> c2;\\n     cout << \\\"Input elements in the first matrix :\\\\n\\\";\\n       for(i=0;i<r1;i++)\\n        {\\n            for(j=0;j<c1;j++)\\n            {\\n               cout << \\\"element -  : [\\\" << i << \\\"][\\\" << j <<\\\"]\\\";\\n               cin >> arr1[i][j];\\n            }\\n        }\\n       cout << \\\"Input elements in the second matrix :\\\\n\\\";\\n       for(i=0;i<r2;i++)\\n        {\\n            for(j=0;j<c2;j++)\\n            {\\n               cout << \\\"element -  : [\\\" << i << \\\"][\\\" << j <<\\\"]\\\";\\n               cin >> brr1[i][j];\\n            }\\n        }\\n     cout << \\\"The first matrix is :\\\\n\\\";\\n     for(i=0;i<r1;i++)\\n     {\\n       for(j=0;j<c1 ;j++)\\n         cout << \\\" \\\" << arr1[i][j] << \\\" \\\";\\n       cout << \\\"\\\\n\\\";\\n     }\\n     cout << \\\"The second matrix is :\\\\n\\\";\\n     for(i=0;i<r2;i++)\\n     {\\n       for(j=0;j<c2 ;j++)\\n         cout << \\\" \\\" << brr1[i][j] << \\\" \\\";\\n        cout << \\\"\\\\n\\\";\\n     }\\n    if(r1 == r2 && c1 == c2)\\n    {\\n        cout << \\\"The Matrices can be compared. \\\\n\\\";\\n        for(i=0; i<r1; i++)\\n        {\\n            for(j=0; j<c2; j++)\\n            {\\n            if(arr1[i][j] != brr1[i][j])\\n            {\\n                   a = 0;\\n                   break;\\n            }\\n            }\\n          }\\n    }\\n    else\\n    {  cout << \\\"The Matrices Cannot be compared :\\\\n\\\";\\n       exit(1);\\n    }\\n    if(a == 1 )\\n    cout << \\\"Two matrices are equal.\\\";\\n    else\\n    cout << \\\"But,two matrices are not equal.\\\";\\n}\\n\")), mdx(\"h3\", null, \"Output\"), mdx(\"pre\", null, mdx(\"code\", {\n    parentName: \"pre\"\n  }, \"Input Rows and Columns of the 1st matrix :\\n2 2\\nInput Rows and Columns of the 2nd matrix :\\n2 2\\nInput elements in the first matrix :\\nelement - [0],[0] : 1\\nelement - [0],[1] : 2\\nelement - [1],[0] : 3\\nelement - [1],[1] : 4\\nInput elements in the second matrix :\\nelement - [0],[0] : 5\\nelement - [0],[1] : 6\\nelement - [1],[0] : 7\\nelement - [1],[1] : 8\\nThe first matrix is :\\n 1  2\\n 3  4\\nThe second matrix is :\\n 5  6\\n 7  8\\nThe Matrices can be compared.\\nBut,two matrices are not equal.\\n\")), mdx(\"h2\", null, \"Java Implementation\"), mdx(\"h3\", null, \"30. Write a Java program to check whether two matrices are equal or not.\"), mdx(\"pre\", null, mdx(\"code\", {\n    parentName: \"pre\",\n    \"className\": \"language-js\"\n  }, \"//Write a Java program to check whether two matrices are equal or not.\\nimport java.util.Scanner;\\npublic class Funycode {\\n    public static void main(String[] args) {\\n           Scanner z=new Scanner(System.in);\\n           int arr1[][]= new int[3][3],brr1[][] = new int[3][3],i, j, r1, c1, r2, c2, a =1;\\n           System.out.println(\\\"Input Rows and Columns of the 1st matrix :\\\\n\\\");\\n           r1 = z.nextInt();\\n           c1 = z.nextInt();\\n           System.out.println(\\\"Input Rows and Columns of the 2nd matrix :\\\\n\\\");\\n           r2 = z.nextInt();\\n           c2 = z.nextInt();\\n             System.out.println(\\\"Input elements in the first matrix :\\\\n\\\");\\n               for(i=0;i<r1;i++)\\n                {\\n                    for(j=0;j<c1;j++)\\n                    {\\n                       System.out.println(\\\"element - : \\\"+\\\"[\\\"+i+\\\"]\\\"+\\\"[\\\"+j+\\\"]\\\");\\n                       arr1[i][j] = z.nextInt();\\n                    }\\n                }\\n               System.out.println(\\\"Input elements in the second matrix :\\\\n\\\");\\n               for(i=0;i<r2;i++)\\n                {\\n                    for(j=0;j<c2;j++)\\n                    {\\n                       System.out.println(\\\"element - : \\\"+\\\"[\\\"+i+\\\"]\\\"+\\\"[\\\"+j+\\\"]\\\");\\n                       brr1[i][j] = z.nextInt();\\n                    }\\n                }\\n              System.out.println(\\\"The first matrix is :\\\\n\\\");\\n             for(i=0;i<r1;i++)\\n             {\\n               for(j=0;j<c1 ;j++)\\n                 System.out.printf(\\\" \\\"+arr1[i][j]+\\\" \\\");\\n                System.out.printf(\\\"\\\\n\\\");\\n             }\\n             System.out.println(\\\"The second matrix is :\\\\n\\\");\\n             for(i=0;i<r2;i++)\\n             {\\n               for(j=0;j<c2 ;j++)\\n                 System.out.printf(\\\" \\\"+brr1[i][j]+\\\" \\\");\\n                System.out.printf(\\\"\\\\n\\\");\\n             }\\n           if(r1 == r2 && c1 == c2)\\n           {\\n                System.out.println(\\\"The Matrices can be compared. \\\\n\\\");\\n                for(i=0; i<r1; i++)\\n                {\\n                     for(j=0; j<c2; j++)\\n                     {\\n                        if(arr1[i][j] != brr1[i][j])\\n                        {\\n                               a = 0;\\n                               break;\\n                        }\\n                     }\\n                  }\\n            }\\n            else\\n            {\\n               System.out.println(\\\"The Matrices Cannot be compared :\\\\n\\\");\\n               System.exit(1);\\n            }\\n            if(a == 1 )\\n              System.out.println(\\\"Two matrices are equal.\\\");\\n            else\\n              System.out.println(\\\"But,two matrices are not equal.\\\");\\n      }\\n}\\n\")), mdx(\"h3\", null, \"Output\"), mdx(\"pre\", null, mdx(\"code\", {\n    parentName: \"pre\"\n  }, \"Input Rows and Columns of the 1st matrix :\\n2 2\\nInput Rows and Columns of the 2nd matrix :\\n2 2\\nInput elements in the first matrix :\\nelement - [0],[0] : 1\\nelement - [0],[1] : 2\\nelement - [1],[0] : 3\\nelement - [1],[1] : 4\\nInput elements in the second matrix :\\nelement - [0],[0] : 5\\nelement - [0],[1] : 6\\nelement - [1],[0] : 7\\nelement - [1],[1] : 8\\nThe first matrix is :\\n 1  2\\n 3  4\\nThe second matrix is :\\n 5  6\\n 7  8\\nThe Matrices can be compared.\\nBut,two matrices are not equal.\\n\")));\n}\n;\nMDXContent.isMDXComponent = true;","rawMDXOutput":"/* @jsx mdx */\nimport { mdx } from '@mdx-js/react';\n/* @jsxRuntime classic */\n/* @jsx mdx */\n\nexport const _frontmatter = {\n  \"title\": \"Write a C/C++/Java program to check whether two matrices are equal or not.\",\n  \"category\": \"Array Program Index\",\n  \"tags\": [\"#c\", \"#c++\", \"#java\", \"#tutorial\"],\n  \"date\": \"2020-04-16T00:00:00.000Z\",\n  \"thumbnailText\": \"Index\"\n};\n\nconst layoutProps = {\n  _frontmatter\n};\nconst MDXLayout = \"wrapper\"\nexport default function MDXContent({\n  components,\n  ...props\n}) {\n  return <MDXLayout {...layoutProps} {...props} components={components} mdxType=\"MDXLayout\">\n    <h2>{`C Implementation`}</h2>\n    <h3>{`30. Write a C program to check whether two matrices are equal or not.`}</h3>\n    <pre><code parentName=\"pre\" {...{\n        \"className\": \"language-c\"\n      }}>{`//Write a C program to check whether two matrices are equal or not.\n#include <stdio.h>\nint main()\n{\n   int arr1[50][50], brr1[50][50],i, j, r1, c1, r2, c2, a =1;\n   printf(\"Input Rows and Columns of the 1st matrix :\\\\n\");\n   scanf(\"%d %d\", &r1, &c1);\n\n   printf(\"Input Rows and Columns of the 2nd matrix :\\\\n\");\n   scanf(\"%d %d\", &r2,&c2);\n     printf(\"Input elements in the first matrix :\\\\n\");\n       for(i=0;i<r1;i++)\n        {\n            for(j=0;j<c1;j++)\n            {\n               printf(\"element - [%d],[%d] : \",i,j);\n               scanf(\"%d\",&arr1[i][j]);\n            }\n        }\n       printf(\"Input elements in the second matrix :\\\\n\");\n       for(i=0;i<r2;i++)\n        {\n            for(j=0;j<c2;j++)\n            {\n               printf(\"element - [%d],[%d] : \",i,j);\n               scanf(\"%d\",&brr1[i][j]);\n            }\n        }\n      printf(\"The first matrix is :\\\\n\");\n     for(i=0;i<r1;i++)\n     {\n       for(j=0;j<c1 ;j++)\n         printf(\" %d \",arr1[i][j]);\n        printf(\"\\\\n\");\n     }\n     printf(\"The second matrix is :\\\\n\");\n     for(i=0;i<r2;i++)\n     {\n       for(j=0;j<c2 ;j++)\n         printf(\" %d \",brr1[i][j]);\n        printf(\"\\\\n\");\n     }\n   if(r1 == r2 && c1 == c2)\n   {\n        printf(\"The Matrices can be compared. \\\\n\");\n        for(i=0; i<r1; i++)\n        {\n             for(j=0; j<c2; j++)\n             {\n            if(arr1[i][j] != brr1[i][j])\n            {\n                   a = 0;\n                   break;\n            }\n             }\n          }\n    }\n    else\n    {  printf(\"The Matrices Cannot be compared :\\\\n\");\n       exit(1);\n    }\n    if(a == 1 )\n    printf(\"Two matrices are equal.\");\n    else\n    printf(\"But,two matrices are not equal.\");\n}\n`}</code></pre>\n    <h3>{`Output`}</h3>\n    <pre><code parentName=\"pre\" {...{}}>{`Input Rows and Columns of the 1st matrix :\n2 2\nInput Rows and Columns of the 2nd matrix :\n2 2\nInput elements in the first matrix :\nelement - [0],[0] : 1\nelement - [0],[1] : 2\nelement - [1],[0] : 3\nelement - [1],[1] : 4\nInput elements in the second matrix :\nelement - [0],[0] : 5\nelement - [0],[1] : 6\nelement - [1],[0] : 7\nelement - [1],[1] : 8\nThe first matrix is :\n 1  2\n 3  4\nThe second matrix is :\n 5  6\n 7  8\nThe Matrices can be compared.\nBut,two matrices are not equal.\n`}</code></pre>\n    <h2>{`C++ Implementation`}</h2>\n    <h3>{`30. Write a C++ program to check whether two matrices are equal or not.`}</h3>\n    <pre><code parentName=\"pre\" {...{\n        \"className\": \"language-c\"\n      }}>{`//Write a C++ program to check whether two matrices are equal or not.\n\n#include <iostream>\nusing namespace std;\nint  main()\n{\n   int arr1[50][50], brr1[50][50],i, j, r1, c1, r2, c2, a =1;\n   cout << \"Input Rows and Columns of the 1st matrix :\\\\n\";\n   scanf(\"%d %d\", &r1, &c1);\n   cout << \"Input Rows and Columns of the 2nd matrix :\\\\n\";\n   cin >> r2 >> c2;\n     cout << \"Input elements in the first matrix :\\\\n\";\n       for(i=0;i<r1;i++)\n        {\n            for(j=0;j<c1;j++)\n            {\n               cout << \"element -  : [\" << i << \"][\" << j <<\"]\";\n               cin >> arr1[i][j];\n            }\n        }\n       cout << \"Input elements in the second matrix :\\\\n\";\n       for(i=0;i<r2;i++)\n        {\n            for(j=0;j<c2;j++)\n            {\n               cout << \"element -  : [\" << i << \"][\" << j <<\"]\";\n               cin >> brr1[i][j];\n            }\n        }\n     cout << \"The first matrix is :\\\\n\";\n     for(i=0;i<r1;i++)\n     {\n       for(j=0;j<c1 ;j++)\n         cout << \" \" << arr1[i][j] << \" \";\n       cout << \"\\\\n\";\n     }\n     cout << \"The second matrix is :\\\\n\";\n     for(i=0;i<r2;i++)\n     {\n       for(j=0;j<c2 ;j++)\n         cout << \" \" << brr1[i][j] << \" \";\n        cout << \"\\\\n\";\n     }\n    if(r1 == r2 && c1 == c2)\n    {\n        cout << \"The Matrices can be compared. \\\\n\";\n        for(i=0; i<r1; i++)\n        {\n            for(j=0; j<c2; j++)\n            {\n            if(arr1[i][j] != brr1[i][j])\n            {\n                   a = 0;\n                   break;\n            }\n            }\n          }\n    }\n    else\n    {  cout << \"The Matrices Cannot be compared :\\\\n\";\n       exit(1);\n    }\n    if(a == 1 )\n    cout << \"Two matrices are equal.\";\n    else\n    cout << \"But,two matrices are not equal.\";\n}\n`}</code></pre>\n    <h3>{`Output`}</h3>\n    <pre><code parentName=\"pre\" {...{}}>{`Input Rows and Columns of the 1st matrix :\n2 2\nInput Rows and Columns of the 2nd matrix :\n2 2\nInput elements in the first matrix :\nelement - [0],[0] : 1\nelement - [0],[1] : 2\nelement - [1],[0] : 3\nelement - [1],[1] : 4\nInput elements in the second matrix :\nelement - [0],[0] : 5\nelement - [0],[1] : 6\nelement - [1],[0] : 7\nelement - [1],[1] : 8\nThe first matrix is :\n 1  2\n 3  4\nThe second matrix is :\n 5  6\n 7  8\nThe Matrices can be compared.\nBut,two matrices are not equal.\n`}</code></pre>\n    <h2>{`Java Implementation`}</h2>\n    <h3>{`30. Write a Java program to check whether two matrices are equal or not.`}</h3>\n    <pre><code parentName=\"pre\" {...{\n        \"className\": \"language-js\"\n      }}>{`//Write a Java program to check whether two matrices are equal or not.\nimport java.util.Scanner;\npublic class Funycode {\n    public static void main(String[] args) {\n           Scanner z=new Scanner(System.in);\n           int arr1[][]= new int[3][3],brr1[][] = new int[3][3],i, j, r1, c1, r2, c2, a =1;\n           System.out.println(\"Input Rows and Columns of the 1st matrix :\\\\n\");\n           r1 = z.nextInt();\n           c1 = z.nextInt();\n           System.out.println(\"Input Rows and Columns of the 2nd matrix :\\\\n\");\n           r2 = z.nextInt();\n           c2 = z.nextInt();\n             System.out.println(\"Input elements in the first matrix :\\\\n\");\n               for(i=0;i<r1;i++)\n                {\n                    for(j=0;j<c1;j++)\n                    {\n                       System.out.println(\"element - : \"+\"[\"+i+\"]\"+\"[\"+j+\"]\");\n                       arr1[i][j] = z.nextInt();\n                    }\n                }\n               System.out.println(\"Input elements in the second matrix :\\\\n\");\n               for(i=0;i<r2;i++)\n                {\n                    for(j=0;j<c2;j++)\n                    {\n                       System.out.println(\"element - : \"+\"[\"+i+\"]\"+\"[\"+j+\"]\");\n                       brr1[i][j] = z.nextInt();\n                    }\n                }\n              System.out.println(\"The first matrix is :\\\\n\");\n             for(i=0;i<r1;i++)\n             {\n               for(j=0;j<c1 ;j++)\n                 System.out.printf(\" \"+arr1[i][j]+\" \");\n                System.out.printf(\"\\\\n\");\n             }\n             System.out.println(\"The second matrix is :\\\\n\");\n             for(i=0;i<r2;i++)\n             {\n               for(j=0;j<c2 ;j++)\n                 System.out.printf(\" \"+brr1[i][j]+\" \");\n                System.out.printf(\"\\\\n\");\n             }\n           if(r1 == r2 && c1 == c2)\n           {\n                System.out.println(\"The Matrices can be compared. \\\\n\");\n                for(i=0; i<r1; i++)\n                {\n                     for(j=0; j<c2; j++)\n                     {\n                        if(arr1[i][j] != brr1[i][j])\n                        {\n                               a = 0;\n                               break;\n                        }\n                     }\n                  }\n            }\n            else\n            {\n               System.out.println(\"The Matrices Cannot be compared :\\\\n\");\n               System.exit(1);\n            }\n            if(a == 1 )\n              System.out.println(\"Two matrices are equal.\");\n            else\n              System.out.println(\"But,two matrices are not equal.\");\n      }\n}\n`}</code></pre>\n    <h3>{`Output`}</h3>\n    <pre><code parentName=\"pre\" {...{}}>{`Input Rows and Columns of the 1st matrix :\n2 2\nInput Rows and Columns of the 2nd matrix :\n2 2\nInput elements in the first matrix :\nelement - [0],[0] : 1\nelement - [0],[1] : 2\nelement - [1],[0] : 3\nelement - [1],[1] : 4\nInput elements in the second matrix :\nelement - [0],[0] : 5\nelement - [0],[1] : 6\nelement - [1],[0] : 7\nelement - [1],[1] : 8\nThe first matrix is :\n 1  2\n 3  4\nThe second matrix is :\n 5  6\n 7  8\nThe Matrices can be compared.\nBut,two matrices are not equal.\n`}</code></pre>\n\n    </MDXLayout>;\n}\n\n;\nMDXContent.isMDXComponent = true;"}}